roku/__init__.py
roku/core.py
roku/discovery.py
roku/proxy.py
roku/server.py
roku/util.py
roku/emulator/__init__.py
roku/emulator/core.py
roku/tests/__init__.py
roku/tests/test_roku.py
pyroku_ng-4.1.1.dist-info/LICENSE
pyroku_ng-4.1.1.dist-info/METADATA
pyroku_ng-4.1.1.dist-info/WHEEL
pyroku_ng-4.1.1.dist-info/top_level.txt
pyroku_ng-4.1.1.dist-info/RECORD
