Metadata-Version: 2.1
Name: pyroku-ng
Version: 4.1.1
Summary: Client for the Roku media player
Home-page: https://github.com/foxy82/python-roku
Author: Jeremy Carbaugh, Foxy82
Author-email: jcarbaugh@gmail.com
License: BSD License
Platform: any
Classifier: Development Status :: 5 - Production/Stable
Classifier: Intended Audience :: Developers
Classifier: License :: OSI Approved :: BSD License
Classifier: Natural Language :: English
Classifier: Programming Language :: Python
Classifier: Programming Language :: Python :: 3.6
Classifier: Programming Language :: Python :: 3.7
Classifier: Programming Language :: Python :: 3.8
License-File: LICENSE
Requires-Dist: requests (<3)
